[{
    "title_kor": "전주콩나물해장국",
    "title_eng": "Bean Sprout Hangover Soup",
    "id": "c804c8fccf69b098bb3cd574c7a5ad6d",
    "kcal": 734,
    "soldout": false,
    "price": 5500,
    "img_src": "/image/c804c8fccf69b098bb3cd574c7a5ad6d.jpg",
    "corner": "KOREAN 1",
    "floor": "b1",
    "payments": 2500,
    "hasImg": true,
    "img_src_more": null
}, {
    "title_kor": "치즈불닭&맑은감자국",
    "title_eng": "Hot and Spicy Chicken with Cheese",
    "id": "ce58c988bd88b2ed0026b9d1c740ac10c790ad6d",
    "kcal": 727,
    "soldout": false,
    "price": 5500,
    "img_src": "/image/ce58c988bd88b2ed0026b9d1c740ac10c790ad6d.jpg",
    "corner": "KOREAN 2",
    "floor": "b1",
    "low_cal": true,
    "payments": 2500,
    "hasImg": true,
    "img_src_more": null
}, {
    "title_kor": "만두버섯전골",
    "title_eng": "Mushroom and Mandu(Dumpling) Hot Pot",
    "id": "b9ccb450bc84c12fc804ace8",
    "kcal": 823,
    "soldout": false,
    "price": 6000,
    "img_src": "/image/b9ccb450bc84c12fc804ace8.jpg",
    "corner": "湯탕맛기픈",
    "floor": "b1",
    "payments": 3500,
    "hasImg": true,
    "img_src_more": null
}, {
    "title_kor": "양지설렁탕",
    "title_eng": "Thick Ox Bone Soup",
    "id": "c591c9c0c124b801d0d5",
    "kcal": 823,
    "soldout": false,
    "price": 6000,
    "img_src": "/image/c591c9c0c124b801d0d5.jpg",
    "corner": "湯탕맛기픈",
    "floor": "b1",
    "payments": 3500,
    "hasImg": true,
    "img_src_more": null
}, {
    "title_kor": "나가사끼라멘",
    "title_eng": "Nakasaki style Ramen",
    "id": "b098ac00c0acb07cb77cba58",
    "kcal": 830,
    "soldout": false,
    "price": 6000,
    "img_src": "/image/b098ac00c0acb07cb77cba58.jpg",
    "corner": "가츠&엔",
    "floor": "b1",
    "payments": 3500,
    "hasImg": true,
    "img_src_more": null
}, {
    "title_kor": "매콤토마토소스돈가스",
    "title_eng": "Spicy Tomato Sauce Pork Cutlet",
    "id": "b9e4cf64d1a0b9c8d1a0c18cc2a4b3c8ac00c2a4",
    "kcal": 852,
    "soldout": false,
    "price": 6500,
    "img_src": "/photo/b9e4cf64d1a0b9c8d1a0c18cc2a4b3c8ac00c2a4-1462849347162.jpg",
    "corner": "가츠&엔",
    "floor": "b1",
    "payments": 4000,
    "hasImg": true,
    "img_src_more": []
}, {
    "title_kor": "돈목살데리야끼필라프",
    "title_eng": "Pork Chuck Pilaf with Teriyaki sauce",
    "id": "b3c8baa9c0b4b370b9acc57cb07cd544b77cd504",
    "kcal": 830,
    "soldout": false,
    "price": 5500,
    "img_src": "/image/b3c8baa9c0b4b370b9acc57cb07cd544b77cd504.jpg",
    "corner": "WESTERN",
    "floor": "b1",
    "payments": 2500,
    "hasImg": true,
    "img_src_more": null
}, {
    "title_kor": "견과류깐풍오므라이스",
    "title_eng": "Omelette Rice with Fried Chicken on Nuts",
    "id": "acacacfcb958ae50d48dc624bbc0b77cc774c2a4",
    "kcal": 855,
    "soldout": false,
    "price": 6000,
    "img_src": "/static/no_image_available.jpg",
    "corner": "WESTERN",
    "floor": "b1",
    "payments": 3500,
    "hasImg": false,
    "img_src_more": null
}, {
    "title_kor": "전주콩나물해장국",
    "title_eng": "Bean Sprout Hangover Soup",
    "id": "c804c8fccf69b098bb3cd574c7a5ad6d",
    "kcal": 734,
    "soldout": false,
    "price": 5500,
    "img_src": "/image/c804c8fccf69b098bb3cd574c7a5ad6d.jpg",
    "corner": "KOREAN 1",
    "floor": "b2",
    "payments": 2500,
    "hasImg": true,
    "img_src_more": null
}, {
    "title_kor": "치즈불닭&맑은감자국",
    "title_eng": "Hot and Spicy Chicken with Cheese",
    "id": "ce58c988bd88b2ed0026b9d1c740ac10c790ad6d",
    "kcal": 727,
    "soldout": false,
    "price": 5500,
    "img_src": "/image/ce58c988bd88b2ed0026b9d1c740ac10c790ad6d.jpg",
    "corner": "KOREAN 2",
    "floor": "b2",
    "low_cal": true,
    "payments": 2500,
    "hasImg": true,
    "img_src_more": null
}, {
    "title_kor": "투움바파스타",
    "title_eng": "Toowoomba Pasta",
    "id": "d22cc6c0bc14d30cc2a4d0c0",
    "kcal": 844,
    "soldout": false,
    "price": 6000,
    "img_src": "/image/d22cc6c0bc14d30cc2a4d0c0.jpg",
    "corner": "Napolipoli",
    "floor": "b2",
    "payments": 3500,
    "hasImg": true,
    "img_src_more": null
}, {
    "title_kor": "콤비네이션피자",
    "title_eng": "Combination pizza ",
    "id": "cf64be44b124c774c158d53cc790",
    "kcal": 900,
    "soldout": true,
    "img_src": "/image/cf64be44b124c774c158d53cc790.jpg",
    "corner": "Napolipoli",
    "floor": "b2",
    "high_cal": true,
    "hasImg": true,
    "img_src_more": null
}, {
    "title_kor": "그린빈스고비커리&치킨티카",
    "title_eng": "Gobi Curry with Green Beans",
    "id": "adf8b9b0be48c2a4ace0be44cee4b9ac0026ce58d0a8d2f0ce74",
    "kcal": 796,
    "soldout": false,
    "price": 6000,
    "img_src": "/image/adf8b9b0be48c2a4ace0be44cee4b9ac0026ce58d0a8d2f0ce74.jpg",
    "corner": "asian*picks",
    "floor": "b2",
    "payments": 3500,
    "hasImg": true,
    "img_src_more": null
}, {
    "title_kor": "나시고랭",
    "title_eng": "Nasi goreng ",
    "id": "b098c2dcace0b7ad",
    "kcal": 804,
    "soldout": false,
    "price": 6000,
    "img_src": "/image/b098c2dcace0b7ad.jpg",
    "corner": "asian*picks",
    "floor": "b2",
    "payments": 3500,
    "hasImg": true,
    "img_src_more": null
}, {
    "title_kor": "해주비빔밥",
    "title_eng": "Bibimbap with Chicken",
    "id": "d574c8fcbe44be54bc25",
    "kcal": 795,
    "soldout": false,
    "price": 6000,
    "img_src": "/image/d574c8fcbe44be54bc25.jpg",
    "corner": "고슬고슬비빈",
    "floor": "b2",
    "payments": 3500,
    "hasImg": true,
    "img_src_more": null
}, {
    "title_kor": "불고기 돌솥비빔밥",
    "title_eng": "Bulgogi Bibimbap in a Stone Pot",
    "id": "bd88ace0ae300020b3ccc1a5be44be54bc25",
    "kcal": 790,
    "soldout": false,
    "price": 6500,
    "img_src": "/image/bd88ace0ae300020b3ccc1a5be44be54bc25.jpg",
    "corner": "고슬고슬비빈",
    "floor": "b2",
    "payments": 4000,
    "hasImg": true,
    "img_src_more": ["/photo/bd88ace0ae300020b3ccc1a5be44be54bc25-1458529325921.jpg"]
}, {
    "title_kor": "(쉐프)플랫브래드새우샌드위치",
    "title_eng": "Chef's Choice",
    "id": "0028c250d5040029d50cb7abbe0cb798b4dcc0c8c6b0c0ccb4dcc704ce58",
    "kcal": 575,
    "soldout": false,
    "price": 6000,
    "img_src": "/static/no_image_available.jpg",
    "corner": "Chef's Counter",
    "floor": "b2",
    "very_low_cal": true,
    "payments": 3500,
    "hasImg": false,
    "img_src_more": null
}, {
    "title_kor": "헬시라이트(오징어콩나물덮밥)",
    "title_eng": "Healthy lite",
    "id": "d5ecc2dcb77cc774d2b80028c624c9d5c5b4cf69b098bb3cb36ebc250029",
    "kcal": 642,
    "soldout": false,
    "price": 6000,
    "img_src": "/static/no_image_available.jpg",
    "corner": "Chef's Counter",
    "floor": "b2",
    "very_low_cal": true,
    "payments": 3500,
    "hasImg": false,
    "img_src_more": null
}, {
    "title_kor": "사천자장면",
    "title_eng": "Sichuan-style Noodles in Black Soybean Sauce",
    "id": "c0accc9cc790c7a5ba74",
    "kcal": 848,
    "soldout": false,
    "price": 6000,
    "img_src": "/image/c0accc9cc790c7a5ba74.jpg",
    "corner": "XingFu China",
    "floor": "b2",
    "payments": 3500,
    "hasImg": true,
    "img_src_more": null
}, {
    "title_kor": "고추잡채덮밥",
    "title_eng": "Shredded and Sauteed Hot Peppers on the Rice",
    "id": "ace0cd94c7a1cc44b36ebc25",
    "kcal": 847,
    "soldout": false,
    "price": 6500,
    "img_src": "/image/ace0cd94c7a1cc44b36ebc25.jpg",
    "corner": "XingFu China",
    "floor": "b2",
    "payments": 4000,
    "hasImg": true,
    "img_src_more": null
}, {
    "title_kor": "함경도두부김치말이국수",
    "title_eng": "Noodles with Tofu and Kimchi Broth",
    "id": "d568acbdb3c4b450bd80ae40ce58b9d0c774ad6dc218",
    "kcal": 716,
    "soldout": false,
    "price": 6000,
    "img_src": "/static/no_image_available.jpg",
    "corner": "우리味각면",
    "floor": "b2",
    "low_cal": true,
    "payments": 3500,
    "hasImg": false,
    "img_src_more": null
}, {
    "title_kor": "열무물냉면",
    "title_eng": "Cold Noodles in Young Summer Radish Kimchi ",
    "id": "c5f4bb34bb3cb0c9ba74",
    "kcal": 731,
    "soldout": false,
    "price": 6000,
    "img_src": "/image/c5f4bb34bb3cb0c9ba74.jpg",
    "corner": "우리味각면",
    "floor": "b2",
    "payments": 3500,
    "hasImg": true,
    "img_src_more": null
}]
